MANIFEST.in
README.txt
setup.cfg
setup.py
docs/HISTORY.txt
docs/INSTALL.txt
docs/LICENSE.GPL
docs/LICENSE.txt
quintagroup/__init__.py
quintagroup.plonecaptchas.egg-info/PKG-INFO
quintagroup.plonecaptchas.egg-info/SOURCES.txt
quintagroup.plonecaptchas.egg-info/dependency_links.txt
quintagroup.plonecaptchas.egg-info/entry_points.txt
quintagroup.plonecaptchas.egg-info/namespace_packages.txt
quintagroup.plonecaptchas.egg-info/not-zip-safe
quintagroup.plonecaptchas.egg-info/requires.txt
quintagroup.plonecaptchas.egg-info/top_level.txt
quintagroup/plonecaptchas/__init__.py
quintagroup/plonecaptchas/captcha.py
quintagroup/plonecaptchas/config.py
quintagroup/plonecaptchas/configure.zcml
quintagroup/plonecaptchas/interfaces.py
quintagroup/plonecaptchas/meta.zcml
quintagroup/plonecaptchas/overrides.zcml
quintagroup/plonecaptchas/setuphandlers.py
quintagroup/plonecaptchas/validate.py
quintagroup/plonecaptchas/version.txt
quintagroup/plonecaptchas/Extensions/Install.py
quintagroup/plonecaptchas/Extensions/__init__.py
quintagroup/plonecaptchas/browser/__init__.py
quintagroup/plonecaptchas/browser/configure.zcml
quintagroup/plonecaptchas/browser/newuser_form.pt
quintagroup/plonecaptchas/browser/register.py
quintagroup/plonecaptchas/browser/register_form.pt
quintagroup/plonecaptchas/profiles/default/metadata.xml
quintagroup/plonecaptchas/profiles/default/quintagroup.plonecaptchas_various.txt
quintagroup/plonecaptchas/profiles/default/skins.xml
quintagroup/plonecaptchas/profiles/register_form/browserlayer.xml
quintagroup/plonecaptchas/profiles/uninstall/import_steps.xml
quintagroup/plonecaptchas/profiles/uninstall/qgplonecaptchas_uninstall.txt
quintagroup/plonecaptchas/profiles/uninstall/skins.xml
quintagroup/plonecaptchas/skins/captchas_contact_info/contact-info.cpt
quintagroup/plonecaptchas/skins/captchas_contact_info/contact-info.cpt.metadata
quintagroup/plonecaptchas/skins/captchas_discussion/discussion_reply.cpy
quintagroup/plonecaptchas/skins/captchas_discussion/discussion_reply.cpy.metadata
quintagroup/plonecaptchas/skins/captchas_discussion/discussion_reply_form.cpt
quintagroup/plonecaptchas/skins/captchas_discussion/discussion_reply_form.cpt.metadata
quintagroup/plonecaptchas/skins/captchas_sendto_form/sendto.cpy
quintagroup/plonecaptchas/skins/captchas_sendto_form/sendto.cpy.metadata
quintagroup/plonecaptchas/skins/captchas_sendto_form/sendto_form.cpt
