Metadata-Version: 1.0
Name: quintagroup.plonecaptchas
Version: 4.2
Summary: quintagroup.plonecaptchas is simple captchas implementation for Plone, designed for validating human input in insecure forms.
Home-page: http://svn.quintagroup.com/products/quintagroup.plonecaptchas
Author: Quintagroup
Author-email: support@quintagroup.com
License: GPL
Keywords: plone captcha
Platform: UNKNOWN
Classifier: Framework :: Plone
Classifier: Programming Language :: Python
Classifier: Topic :: Software Development :: Libraries :: Python Modules
